lithopscloud/__init__.py
lithopscloud/main.py
lithopscloud/modules/__init__.py
lithopscloud/modules/api_key.py
lithopscloud/modules/config_builder.py
lithopscloud/modules/config_verification.py
lithopscloud/modules/cos.py
lithopscloud/modules/runtime.py
lithopscloud/modules/utils.py
lithopscloud/modules/cloud_functions/__init__.py
lithopscloud/modules/cloud_functions/cloud_function.py
lithopscloud/modules/cloud_functions/defaults.yaml
lithopscloud/modules/cloud_functions/verify.py
lithopscloud/modules/code_engine/__init__.py
lithopscloud/modules/code_engine/code_engine.py
lithopscloud/modules/code_engine/defaults.yaml
lithopscloud/modules/code_engine/runtime.py
lithopscloud/modules/code_engine/verify.py
lithopscloud/modules/cos-package/__init__.py
lithopscloud/modules/cos-package/verify.py
lithopscloud/modules/gen2/__init__.py
lithopscloud/modules/gen2/endpoint.py
lithopscloud/modules/gen2/image.py
lithopscloud/modules/gen2/profile.py
lithopscloud/modules/gen2/ssh_key.py
lithopscloud/modules/gen2/verify.py
lithopscloud/modules/gen2/vpc.py
lithopscloud/modules/gen2/lithops/__init__.py
lithopscloud/modules/gen2/lithops/defaults.yaml
lithopscloud/modules/gen2/lithops/dismantle.py
lithopscloud/modules/gen2/lithops/endpoint.py
lithopscloud/modules/gen2/lithops/image.py
lithopscloud/modules/gen2/lithops/profile.py
lithopscloud/modules/gen2/lithops/runtime.py
lithopscloud/modules/gen2/lithops/ssh_key.py
lithopscloud/modules/gen2/lithops/vpc.py
lithopscloud/modules/gen2/ray/__init__.py
lithopscloud/modules/gen2/ray/api_key.py
lithopscloud/modules/gen2/ray/defaults.yaml
lithopscloud/modules/gen2/ray/defaults_pr.yaml
lithopscloud/modules/gen2/ray/endpoint.py
lithopscloud/modules/gen2/ray/floating_ip.py
lithopscloud/modules/gen2/ray/image.py
lithopscloud/modules/gen2/ray/profile.py
lithopscloud/modules/gen2/ray/ssh_key.py
lithopscloud/modules/gen2/ray/vpc.py
lithopscloud/modules/gen2/ray/workers.py
lithopscloud/modules/local_host/__init__.py
lithopscloud-1.0.0b98.dist-info/LICENSE
lithopscloud-1.0.0b98.dist-info/METADATA
lithopscloud-1.0.0b98.dist-info/WHEEL
lithopscloud-1.0.0b98.dist-info/top_level.txt
lithopscloud-1.0.0b98.dist-info/RECORD
