Metadata-Version: 2.1
Name: lithopscloud
Version: 1.0.0b98
Summary: Interactive tool for generation of lithops configuration
Home-page: https://github.com/lithops-cloud/lithopscloud
Author: kpavel
Author-email: kpavel@il.ibm.com
Classifier: Programming Language :: Python :: 3
Requires-Python: >=3.6
License-File: LICENSE
Requires-Dist: click (>=8.0.1)
Requires-Dist: inquirer (>=2.7.0)
Requires-Dist: ibm-cloud-sdk-core
Requires-Dist: ibm-platform-services
Requires-Dist: ibm-cos-sdk
Requires-Dist: PyYAML (>=5.4.1)
Requires-Dist: ibm-code-engine-sdk
Requires-Dist: ibm-watson
Requires-Dist: docker (>=5.0.3)
Requires-Dist: lithops (>=2.5.4)
Requires-Dist: ibm-vpc
